chprog/chprog.py
chprog-2.5.3.dist-info/licenses/LICENSE
chprog-2.5.3.dist-info/METADATA
chprog-2.5.3.dist-info/WHEEL
chprog-2.5.3.dist-info/entry_points.txt
chprog-2.5.3.dist-info/top_level.txt
chprog-2.5.3.dist-info/RECORD
